wirepas_console/__about__.py
wirepas_console/__init__.py
wirepas_console/console.py
wirepas_console/backend/__init__.py
wirepas_console/backend/mqtt_connection.py
wirepas_console/backend/settings.py
wirepas_console/frontend/__init__.py
wirepas_console/resources/static/favicon.ico
wirepas_console/resources/static/index.html
wirepas_console/resources/static/css/app.583437ed.css
wirepas_console/resources/static/css/vendor.529baf94.css
wirepas_console/resources/static/fonts/KFOkCnqEu92Fr1MmgVxIIzQ.9391e6e2.woff
wirepas_console/resources/static/fonts/KFOlCnqEu92Fr1MmEU9fBBc-.ddd11dab.woff
wirepas_console/resources/static/fonts/KFOlCnqEu92Fr1MmSU5fBBc-.877b9231.woff
wirepas_console/resources/static/fonts/KFOlCnqEu92Fr1MmWUlfBBc-.0344cc3c.woff
wirepas_console/resources/static/fonts/KFOlCnqEu92Fr1MmYUtfBBc-.b555d228.woff
wirepas_console/resources/static/fonts/KFOmCnqEu92Fr1Mu4mxM.9b78ea3b.woff
wirepas_console/resources/static/fonts/flUhRq6tzZclQEJ-Vdg-IuiaDsNa.0d57c481.woff
wirepas_console/resources/static/fonts/flUhRq6tzZclQEJ-Vdg-IuiaDsNcIhQ8tQ.ae520e14.woff2
wirepas_console/resources/static/fonts/roboto-mono-v13-latin-regular.498042b7.woff
wirepas_console/resources/static/icons/favicon-128x128.png
wirepas_console/resources/static/icons/favicon-16x16.png
wirepas_console/resources/static/icons/favicon-32x32.png
wirepas_console/resources/static/icons/favicon-96x96.png
wirepas_console/resources/static/js/2.6074028a.js
wirepas_console/resources/static/js/app.0731b4f9.js
wirepas_console/resources/static/js/vendor.20c9ec0c.js
wirepas_console/resources/templates/.gitkeep
wirepas_console-1.0.dist-info/LICENSE
wirepas_console-1.0.dist-info/METADATA
wirepas_console-1.0.dist-info/WHEEL
wirepas_console-1.0.dist-info/entry_points.txt
wirepas_console-1.0.dist-info/top_level.txt
wirepas_console-1.0.dist-info/RECORD
