Metadata-Version: 2.1
Name: wirepas-console
Version: 1.0
Summary: A tool for configuring and monitoring Wirepas networks
Home-page: https://github.com/wirepas/wirepas-console
Author: Wirepas Ltd
Author-email: opensource@wirepas.com
License: All Rights Reserved
Keywords: wirepas connectivity iot mesh terminal backend
Platform: UNKNOWN
Classifier: Development Status :: 5 - Production/Stable
Classifier: Intended Audience :: Developers
Classifier: License :: Free To Use But Restricted
Classifier: Topic :: Communications
Classifier: Topic :: Terminals
Classifier: Programming Language :: Python :: 3
Requires-Dist: appdirs (==1.4.4)
Requires-Dist: pywebview (==3.4)
Requires-Dist: tornado (==6.1)
Requires-Dist: wirepas-mesh-messaging (==1.1)
Requires-Dist: wirepas-mqtt-library (==1.0)
